finance_structs-0.1.0.dist-info/METADATA
finance_structs-0.1.0.dist-info/WHEEL
finance_structs-0.1.0.dist-info/license_files/LICENSE
finance_structs/tests/test_all.py
finance_structs/__init__.py
finance_structs/finance_structs.abi3.so
finance_structs-0.1.0.dist-info/RECORD
